rwpp/__init__.py
rwpp/main.py
rwpp-0.1.5.dist-info/LICENSE
rwpp-0.1.5.dist-info/METADATA
rwpp-0.1.5.dist-info/WHEEL
rwpp-0.1.5.dist-info/entry_points.txt
rwpp-0.1.5.dist-info/RECORD
