Metadata-Version: 2.1
Name: rwpp
Version: 0.1.5
Summary: Reddit Wallpaper Puller, a simple CLI to pull wallpapers from Reddit.
Author: Ducky
Author-email: duckbox007@pm.me
Requires-Python: >=3.8,<4.0
Classifier: Programming Language :: Python :: 3
Classifier: Programming Language :: Python :: 3.8
Classifier: Programming Language :: Python :: 3.9
Classifier: Programming Language :: Python :: 3.10
Classifier: Programming Language :: Python :: 3.11
Requires-Dist: redditwarp (>=1.0.0,<2.0.0)
Requires-Dist: requests (>=2.28.2,<3.0.0)
Requires-Dist: typer[all] (>=0.7.0,<0.8.0)
